[ {"dept": "Biosciences and Bioengineering", "name": "KULKARNI ALARK SHRIPAD"}, {"dept": "Biosciences and Bioengineering", "name": "SUBBI RAMI REDDY TADI"}, {"dept": "Biosciences and Bioengineering", "name": "UMESH KUMAR"}, {"dept": "Biosciences and Bioengineering", "name": "GARIMA SINGH"}, {"dept": "Biosciences and Bioengineering", "name": "RAJANI KANT RAI"}, {"dept": "Biosciences and Bioengineering", "name": "EKTA KUMARI"}, {"dept": "Biosciences and Bioengineering", "name": "PROMI DAS"}, {"dept": "Biosciences and Bioengineering", "name": "ANKUR MISHRA"}, {"dept": "Biosciences and Bioengineering", "name": "BHANUPRIYA CHOUHAN"}, {"dept": "Biosciences and Bioengineering", "name": "SHAGUN SRIVASTAVA"}, {"dept": "Biosciences and Bioengineering", "name": "RISHABH SINGH"}, {"dept": "Biosciences and Bioengineering", "name": "SHRAYAN KUMAR DAS"}, {"dept": "Biosciences and Bioengineering", "name": "GOWTHAM SELVARAJ"}, {"dept": "Biosciences and Bioengineering", "name": "SOMYA SRIVASTAVA"}, {"dept": "Biosciences and Bioengineering", "name": "IFFAT JAHAN"}, {"dept": "Biosciences and Bioengineering", "name": "AMBUJ SRIVASTAVA"}, {"dept": "Biosciences and Bioengineering", "name": "KORE SUKHADEV APPANNA"}, {"dept": "Biosciences and Bioengineering", "name": "NIKHIL GUPTA"}, {"dept": "Biosciences and Bioengineering", "name": "MAYENGBAM SHYAMANANDA SINGH"}, {"dept": "Biosciences and Bioengineering", "name": "MOHD FARHAN SIDDIQUI"}, {"dept": "Biosciences and Bioengineering", "name": "AMRUTHA BASKER"}, {"dept": "Biosciences and Bioengineering", "name": "RATNAKARAM SIVA KUMAR RAJU"}, {"dept": "Biosciences and Bioengineering", "name": "PEVEKAR VINAYAK SURESH"}, {"dept": "Biosciences and Bioengineering", "name": "SUMANTH GOVATHATI"}, {"dept": "Biosciences and Bioengineering", "name": "ASHISH ANAND"}, {"dept": "Biosciences and Bioengineering", "name": "NAVEEN BEDI"}, {"dept": "Biosciences and Bioengineering", "name": "AJAY KUMAR SAHI"}, {"dept": "Biosciences and Bioengineering", "name": "NEITHOO"}, {"dept": "Biosciences and Bioengineering", "name": "S VANITHA"}, {"dept": "Biosciences and Bioengineering", "name": "VINOH SWU"}, {"dept": "Biosciences and Bioengineering", "name": "M.Tech. 2014"}, {"dept": "Biosciences and Bioengineering", "name": "PREETI  CHAUHAN"}, {"dept": "Biosciences and Bioengineering", "name": "MRINAL  SHARMA"}, {"dept": "Biosciences and Bioengineering", "name": "PALLAVI"}, {"dept": "Biosciences and Bioengineering", "name": "ROHIT  P  JAMES"}, {"dept": "Biosciences and Bioengineering", "name": "MIMI  ADHIKARY"}, {"dept": "Biosciences and Bioengineering", "name": "ANIRBAN  JANA"}, {"dept": "Biosciences and Bioengineering", "name": "SONA  SHARMA"}, {"dept": "Biosciences and Bioengineering", "name": "PRIYANKA  DUBEY"}, {"dept": "Biosciences and Bioengineering", "name": "ARNAB  ROY"}, {"dept": "Biosciences and Bioengineering", "name": "ADITYA GOPALAKRISHNA RAO"}, {"dept": "Biosciences and Bioengineering", "name": "ANJALI SINGH"}, {"dept": "Biosciences and Bioengineering", "name": "SAKSHI TIWARI"}, {"dept": "Biosciences and Bioengineering", "name": "VIVEK   PRAKASH"}, {"dept": "Biosciences and Bioengineering", "name": "VIJAY PRAKASH YADAV"}, {"dept": "Biosciences and Bioengineering", "name": "RAMYA  M"}, {"dept": "Biosciences and Bioengineering", "name": "AMIT  KUMAR"}, {"dept": "Biosciences and Bioengineering", "name": "SMITA  DAS"}, {"dept": "Biosciences and Bioengineering", "name": "MD RAMIZ RAZA"}, {"dept": "Biosciences and Bioengineering", "name": "NAVODIT KUMAR SINGH"}, {"dept": "Biosciences and Bioengineering", "name": "NIKHIL  KP"}, {"dept": "Biosciences and Bioengineering", "name": "VIKAS RANJAN"}, {"dept": "Biosciences and Bioengineering", "name": "SHWETA   SINGH"}, {"dept": "Biosciences and Bioengineering", "name": "ROHIT SHESHRAO GHODKE"}, {"dept": "Biosciences and Bioengineering", "name": "TARUN   VERMA"}, {"dept": "Biosciences and Bioengineering", "name": "KETAN ASHOK GANAR"}, {"dept": "Biosciences and Bioengineering", "name": "KANCHAN CHAUHAN"}, {"dept": "Biosciences and Bioengineering", "name": "SANDEEP INIGO SURIN"}, {"dept": "Biosciences and Bioengineering", "name": "INES LOBO ANTUNES"}, {"dept": "Biosciences and Bioengineering", "name": "KAUSHALESH GUPTA"}, {"dept": "Biosciences and Bioengineering", "name": "GARGI MUKHOPADHYAY"}, {"dept": "Biosciences and Bioengineering", "name": "NAVEEN BIJALWAN"}, {"dept": "Biosciences and Bioengineering", "name": "MANJU NAGAR"}, {"dept": "Biosciences and Bioengineering", "name": "AKASH"}]
